src/__init__.py
src/main.py
src/cli/__init__.py
src/cli/menu.py
src/cli/prompts.py
src/cli/styles.py
src/models/__init__.py
src/models/task.py
src/services/__init__.py
src/services/task_manager.py
src/storage/__init__.py
src/storage/json_storage.py
mesumali_console_task_manager-1.0.3.dist-info/METADATA
mesumali_console_task_manager-1.0.3.dist-info/WHEEL
mesumali_console_task_manager-1.0.3.dist-info/entry_points.txt
mesumali_console_task_manager-1.0.3.dist-info/licenses/LICENSE
mesumali_console_task_manager-1.0.3.dist-info/RECORD
