Metadata-Version: 2.4
Name: mesumali-console-task-manager
Version: 1.0.3
Summary: A console-based task management application
Project-URL: Homepage, https://github.com/mesumali/console-task-manager
Project-URL: Repository, https://github.com/mesumali/console-task-manager
Author-email: Mesum Ali <s.mesumali99@gmail.com>
License: MIT
License-File: LICENSE
Keywords: cli,console,manager,task,todo
Classifier: Environment :: Console
Classifier: License :: OSI Approved :: MIT License
Classifier: Operating System :: OS Independent
Classifier: Programming Language :: Python :: 3
Classifier: Programming Language :: Python :: 3.13
Classifier: Topic :: Utilities
Requires-Python: >=3.13
Requires-Dist: inquirerpy>=0.3.4
